Adithya_STT/__init__.py
Adithya_STT-1.0.1.dist-info/METADATA
Adithya_STT-1.0.1.dist-info/WHEEL
Adithya_STT-1.0.1.dist-info/top_level.txt
Adithya_STT-1.0.1.dist-info/RECORD
