Metadata-Version: 2.1
Name: Adithya_STT
Version: 1.0.1
Summary: This is the speech to text package using selenium and webdriver-manager
Author: Adithya
Author-email: adhithya6281@gmail.com
